uznlp/UzbekStemmer.py
uznlp/__init__.py
uznlp-0.0.1.dist-info/LICENSE
uznlp-0.0.1.dist-info/METADATA
uznlp-0.0.1.dist-info/WHEEL
uznlp-0.0.1.dist-info/top_level.txt
uznlp-0.0.1.dist-info/RECORD
