Metadata-Version: 2.1
Name: uznlp
Version: 0.0.1
Summary: nltk for Uzbek language
Home-page: https://github.com/OllaberganYuldashov/uznlp
Author: Ollabergan Yuldashov
Author-email: ollaberganyuldashov@gmail.com
Project-URL: Bug Tracker, https://github.com/OllaberganYuldashov/uznlp
Classifier: Programming Language :: Python :: 3
Classifier: License :: OSI Approved :: MIT License
Classifier: Operating System :: OS Independent
Requires-Python: >=3.6
License-File: LICENSE
